youtubeRenderer/__init__.py
youtubeRenderer/custom_exception.py
youtubeRenderer/logger.py
youtubeRenderer/youtube.py
youtuberenderer-0.0.1.dist-info/LICENSE
youtuberenderer-0.0.1.dist-info/METADATA
youtuberenderer-0.0.1.dist-info/WHEEL
youtuberenderer-0.0.1.dist-info/top_level.txt
youtuberenderer-0.0.1.dist-info/RECORD
